kraken.py
kraken123-0.5.0.dist-info/licenses/LICENSE
kraken123-0.5.0.dist-info/METADATA
kraken123-0.5.0.dist-info/WHEEL
kraken123-0.5.0.dist-info/top_level.txt
kraken123-0.5.0.dist-info/RECORD
