Metadata-Version: 2.4
Name: kraken123
Version: 0.5.0
Summary: A virus package FOR EDUCATIONAL PURPOSES ONLY
Author-email: bluecode2 <bl00xkidd@gmail.com>
License-Expression: MIT
Project-URL: Homepage, https://github.com/bluecodeyt12-maker/Kraken-Virus
Project-URL: Repository, https://github.com/bluecodeyt12-maker/Kraken-Virus
Project-URL: Issues, https://github.com/bluecodeyt12-maker/Kraken-Virus/issues
Keywords: kraken,virus,security
Classifier: Programming Language :: Python :: 3
Classifier: Programming Language :: Python :: 3.8
Classifier: Programming Language :: Python :: 3.9
Classifier: Programming Language :: Python :: 3.10
Classifier: Programming Language :: Python :: 3.11
Classifier: Programming Language :: Python :: 3.12
License-File: LICENSE
Requires-Dist: numpy>=1.21.0
Requires-Dist: keras>=3.0.0
Requires-Dist: scapy>=2.5.0
Requires-Dist: paramiko>=3.2.0
Requires-Dist: requests>=2.31.0
Requires-Dist: cryptography>=41.0.0
Requires-Dist: dnspython>=2.4.0
Requires-Dist: beautifulsoup4>=4.12.0
Requires-Dist: python-whois>=0.8.0
Requires-Dist: shodan>=1.29.0
Requires-Dist: python-nmap>=0.7.1
Requires-Dist: fake-useragent>=1.4.0
Requires-Dist: geoip2>=4.7.0
Requires-Dist: psutil>=5.9.0
Requires-Dist: pyautogui>=0.9.54
Requires-Dist: pyperclip>=1.8.2
Requires-Dist: sounddevice>=0.4.6
Requires-Dist: opencv-python>=4.8.0
Requires-Dist: pillow>=10.0.0
Requires-Dist: browserhistory>=0.1.2
Requires-Dist: pynput>=1.7.6
Requires-Dist: aiohttp>=3.8.5
Requires-Dist: aiosmtplib>=2.0.0
Requires-Dist: pywin32>=306; platform_system == "Windows"
Requires-Dist: netifaces>=0.11.0; platform_system != "Windows"
Requires-Dist: pymssql>=2.2.7; platform_system == "Windows"
Requires-Dist: mysql-connector-python>=8.1.0
Requires-Dist: secretstorage>=3.3.3; platform_system == "Linux"
Requires-Dist: gnupg>=2.3.1
Requires-Dist: pyopenssl>=23.2.0
Requires-Dist: keyring>=24.2.0
Requires-Dist: impacket>=0.10.0; platform_system == "Windows"
Requires-Dist: win32-setctime>=1.1.0; platform_system == "Windows"
Provides-Extra: dev
Requires-Dist: pytest>=7.0.0; extra == "dev"
Requires-Dist: black>=23.0.0; extra == "dev"
Requires-Dist: flake8>=6.0.0; extra == "dev"
Requires-Dist: mypy>=1.0.0; extra == "dev"
Dynamic: license-file
